{
  "size": {
    "spacing": {
      "100": {
        "value": "8px"
      },
      "200": {
        "value": "12px"
      },
      "300": {
        "value": "16px"
      },
      "400": {
        "value": "20px"
      },
      "500": {
        "value": "24px"
      },
      "600": {
        "value": "28px"
      },
      "700": {
        "value": "32px"
      },
      "800": {
        "value": "36px"
      },
      "900": {
        "value": "40px"
      },
      "1000": {
        "value": "48px"
      },
      "1100": {
        "value": "56px"
      },
      "1200": {
        "value": "64px"
      },
      "1300": {
        "value": "72px"
      },
      "1400": {
        "value": "80px"
      },
      "1500": {
        "value": "88px"
      },
      "1600": {
        "value": "96px"
      },
      "1700": {
        "value": "124px"
      },
      "1800": {
        "value": "148px"
      }
    }
  }
}